lab0/SimpleCircuit.v
module SimpleCircuit(
    input a,
    input b,
    input c,
    output f
);
    wire d;

    assign d = a || b;
    assign f = d && c;
endmodule

lab0/SimpleCircuit.t.v
module SimpleCircuit_test;
    reg [3:0] counter;
    wire out;

    SimpleCircuit circuit_under_test(
        .a(counter[2]),
        .b(counter[1]),
        .c(counter[0]),
        .f(out)
    );

    always @( * ) begin
        if (counter[3]) begin
            $finish;
        end
    end

    initial begin
        $dumpfile("SimpleCircuit_test.vcd");
        $dumpvars;

        counter = 4'b0000;

        while (1) begin
        #1  // Delay for one second
            counter = counter + 3'b001;
        end
    end

endmodule

lab0/SimpleCircuit_test.vcd
$date
	Sat Sep 22 15:37:10 2018
$end
$version
	Icarus Verilog
$end
$timescale
	1s
$end
$scope module SimpleCircuit_test $end
$var wire 1 ! out $end
$var reg 4 " counter [3:0] $end
$scope module circuit_under_test $end
$var wire 1 # a $end
$var wire 1 $ b $end
$var wire 1 % c $end
$var wire 1 & d $end
$var wire 1 ! f $end
$upscope $end
$upscope $end
$enddefinitions $end
#0
$dumpvars
0&
0%
0$
0#
b0 "
0!
$end
#1
1%
b1 "
#2
1&
1$
0%
b10 "
#3
1!
1%
b11 "
#4
0!
1#
0$
0%
b100 "
#5
1!
1%
b101 "
#6
0!
1$
0%
b110 "
#7
1!
1%
b111 "
#8
0&
0!
0#
0$
0%
b1000 "
