lab4/Stoplight.v
//==============================================================================
// Stoplight Module for Lab 4
//
// Note on lights:
// 	Each bit represents the on/off signal for a light.
// 	Bit | Light
// 	------------
// 	0   | Red
// 	1   | Yellow
// 	2   | Green
//==============================================================================

module Stoplight(
	input            clk,         // Clock signal
	input            rst,         // Reset signal for FSM
	input            car_present, // Is there a car on Prospect?
	output reg [2:0] light_pros,  // Prospect Avenue Light
	output reg [2:0] light_wash   // Washington Road Light
);

	// Variables for state and next state
	reg [3:0] state;
	reg [3:0] next_state;

	// Declare State Names Here
	localparam STATE_ZERO  = 4'd0;
	localparam STATE_ONE   = 4'd1;
	localparam STATE_TWO   = 4'd2;
	localparam STATE_THREE = 4'd3;
	localparam STATE_FOUR  = 4'd4;
	localparam STATE_FIVE  = 4'd5;
	localparam STATE_SIX   = 4'd6;
	localparam STATE_SEVEN = 4'd7;
	localparam STATE_EIGHT = 4'd8;
	localparam STATE_NINE  = 4'd9;
	localparam STATE_TEN   = 4'd10;

	// Light Colors
	localparam RED = 3'b001;
	localparam YLW = 3'b010;
	localparam GRN = 3'b100;

	// Output Combinational Logic
	always @( * ) begin
		light_pros = 3'b000;
		light_wash = 3'b000;

		// Write your output logic here
		if (state == STATE_ZERO) begin
			light_wash = GRN;
			light_pros = RED;
		end
		if (state == STATE_ONE) begin
			light_wash = GRN;
			light_pros = RED;
		end
		if (state == STATE_TWO) begin
			light_wash = GRN;
			light_pros = RED;
		end
		if (state == STATE_THREE) begin
			light_wash = GRN;
			light_pros = RED;
		end
		if (state == STATE_FOUR) begin
			light_wash = YLW;
			light_pros = RED;	
		end
		if (state == STATE_FIVE) begin
			light_wash = RED;
			light_pros = GRN;
		end
		if (state == STATE_SIX) begin
			light_wash = RED;
			light_pros = GRN;
		end
		if (state == STATE_SEVEN) begin
			light_wash = RED;
			light_pros = GRN;
		end
		if (state == STATE_EIGHT) begin
			light_wash = RED;
			light_pros = GRN;
		end
		if (state == STATE_NINE) begin
			light_wash = RED;
			light_pros = YLW;
		end
	end

	// Next State Combinational Logic
	always @( * ) begin
		if (state == STATE_ZERO) begin
			next_state = STATE_ONE;
		end 
		else if (state == STATE_ONE) begin
			next_state = STATE_TWO;
		end 
		else if (state == STATE_TWO) begin
			next_state = STATE_THREE;
		end 
		else if (state == STATE_THREE) begin
			if (car_present) begin
				next_state = STATE_FOUR;
			end
			else begin
				next_state = STATE_THREE;
			end
		end
		else if (state == STATE_FOUR) begin
			next_state = STATE_FIVE;
		end 
		else if (state == STATE_FIVE) begin
			next_state = STATE_SIX;
		end 
		else if (state == STATE_SIX) begin
			next_state = STATE_SEVEN;
		end 
		else if (state == STATE_SEVEN) begin
			next_state = STATE_EIGHT;
		end 
		else if (state == STATE_EIGHT) begin
			next_state = STATE_NINE;
		end 
		else if (state == STATE_NINE) begin
			next_state = STATE_ZERO;
		end
	end

	// State Update Sequential Logic
	always @(posedge clk) begin
		if (rst) begin
			// Update state to reset state
			state <= STATE_ONE;
		end
		else begin
			// Update state to next state
			state <= next_state;
		end
	end

endmodule

lab4/Stoplight.t.v
//==============================================================================
// Stoplight Testbench Module for Lab 4
//==============================================================================
`timescale 1ns/100ps

`include "Stoplight.v"

module StoplightTest;

	// Local Vars
	reg clk = 1;
	reg rst = 0;
	reg car = 0;
	wire [2:0] lp, lw;

	// Light Colors
	localparam GRN = 3'b100;
	localparam YLW = 3'b010;
	localparam RED = 3'b001;

	// VCD Dump
	initial begin
		$dumpfile("StoplightTest.vcd");
		$dumpvars;
	end

	// Stoplight Module
	Stoplight light(
		.clk        (clk),
		.rst        (rst),
		.car_present(car),
		.light_pros (lp),
		.light_wash (lw)
	);

	// Clock
	always begin
		#2.5 clk = ~clk;
	end

	// Main Test Logic
	initial begin
		// reset goes high
		$display("\nTime 1: Resetting the Controller (Washington -> GREEN)...");
		#1; rst = 1; @(posedge clk);
		
		// reset goes low
		$display("\nTime 6: Reset goes to low (Washington stays on GREEN)...");
		#4; rst = 0; @(posedge clk);
		#1;

		// check correct colours
		if (lp != RED || lw != GRN) begin
			$display("Error at time %t", $time);
		end
		
		// car signal goes high (car waiting on prospect)
		$display("\nTime 41: Car arrives on prospect (Washington -> YELLOW)...");
		#34; car = 1; @(posedge clk);
		#1;
		if (lp != RED || lw != YLW) begin
			$display("Error at time %t", $time);
		end
		
		#4; // at time 46 
		$display("\nTime 46: Car still waiting (Prospect -> GREEN)...");
		#1;
		if (lp != GRN || lw != RED) begin
			$display("Error at time %t", $time);
		end
		
		#4; car = 0; @(posedge clk); // at time 51
		$display("\nTime 51: Car gets green, has moved, car signal goes low ...");
		#1;
		if (lp != GRN || lw != RED) begin
			$display("Error at time %t", $time);
		end
		
		#14; car = 1; @(posedge clk); // at time 66
		$display("\nTime 66: Prospect green for 20 sec. More cars arrive (Prospect -> YELLOW) ...");
		#1;
		if (lp != YLW || lw != RED) begin
			$display("Error at time %t", $time);
		end
		
		#4; // at time 71
		$display("\nTime 71: Car signal still high, light finishes change (Washington -> GREEN, Propsect -> RED) ...");
		#1;
		if (lp != RED || lw != GRN) begin
			$display("Error at time %t", $time);
		end
		
		#4; // at time 76
		$display("\nTime 76: One car still trapped on Prospect ...");
		#1;
		if (lp != RED || lw != GRN) begin
			$display("Error at time %t", $time);
		end
		
		#9; car = 0; @(posedge clk); // at time 86
		$display("\nTime 86: Car makes right on red, car signal low ...");
		#1;
		if (lp != RED || lw != GRN) begin
			$display("Error at time %t", $time);
		end
		
		#19; car = 1; @(posedge clk); // at time 106
		$display("\nTime 106: Car appears, signal goes high (Washigton -> YELLOW) ...");
		#1;
		if (lp != RED || lw != YLW) begin
			$display("Error at time %t", $time);
		end
		
		#9; car = 0; @(posedge clk); // at time 116
		$display("\nTime 116: Car turns, signal goes low (Washigton is RED) ...");
		#1;
		if (lp != GRN || lw != RED) begin
			$display("Error at time %t", $time);
		end
		
		#14; car = 1; @(posedge clk); // at time 131
		$display("\nTime 131: Another car shows up (but it has been 20 sec.) ...");
		#1;
		if (lp != YLW || lw != RED) begin
			$display("Error at time %t", $time);
		end
		
		#4; car = 0; @(posedge clk); // at time 136
		$display("\nTime 136: Last car leaves ...");
		#1;
		if (lp != RED || lw != GRN) begin
			$display("Error at time %t", $time);
		end
		#3; 
		$finish;
	end

endmodule

lab4/StoplightTest.vcd
$date
	Tue Nov  6 20:07:30 2018
$end
$version
	Icarus Verilog
$end
$timescale
	100ps
$end
$scope module StoplightTest $end
$var wire 3 ! lw [2:0] $end
$var wire 3 " lp [2:0] $end
$var reg 1 # car $end
$var reg 1 $ clk $end
$var reg 1 % rst $end
$scope module light $end
$var wire 1 # car_present $end
$var wire 1 $ clk $end
$var wire 1 % rst $end
$var reg 3 & light_pros [2:0] $end
$var reg 3 ' light_wash [2:0] $end
$var reg 4 ( next_state [3:0] $end
$var reg 4 ) state [3:0] $end
$upscope $end
$upscope $end
$enddefinitions $end
#0
$dumpvars
bx )
bx (
bx '
bx &
0%
1$
0#
bx "
bx !
$end
#10
1%
#25
0$
#50
b10 (
b100 !
b100 '
b1 "
b1 &
b1 )
1$
#75
0$
#90
0%
#100
b11 (
b100 !
b100 '
b1 "
b1 &
b10 )
1$
#125
0$
#150
b100 !
b100 '
b1 "
b1 &
b11 )
1$
#175
0$
#200
1$
#225
0$
#250
1$
#275
0$
#300
1$
#325
0$
#350
1$
#375
0$
#400
1$
#425
0$
#450
b10 !
b10 '
b1 "
b1 &
b100 )
b101 (
1$
1#
#475
0$
#500
b110 (
b1 !
b1 '
b100 "
b100 &
b101 )
1$
#525
0$
#550
b111 (
b1 !
b1 '
b100 "
b100 &
b110 )
1$
0#
#575
0$
#600
b1000 (
b1 !
b1 '
b100 "
b100 &
b111 )
1$
#625
0$
#650
b1001 (
b1 !
b1 '
b100 "
b100 &
b1000 )
1$
#675
0$
#700
b0 (
b1 !
b1 '
b10 "
b10 &
b1001 )
1$
1#
#725
0$
#750
b1 (
b100 !
b100 '
b1 "
b1 &
b0 )
1$
#775
0$
#800
b10 (
b100 !
b100 '
b1 "
b1 &
b1 )
1$
#825
0$
#850
b11 (
b100 !
b100 '
b1 "
b1 &
b10 )
1$
#875
0$
#900
b100 !
b100 '
b1 "
b1 &
b11 )
1$
0#
#925
0$
#950
1$
#975
0$
#1000
1$
#1025
0$
#1050
1$
#1075
0$
#1100
b10 !
b10 '
b1 "
b1 &
b100 )
b101 (
1$
1#
#1125
0$
#1150
b110 (
b1 !
b1 '
b100 "
b100 &
b101 )
1$
#1175
0$
#1200
b111 (
b1 !
b1 '
b100 "
b100 &
b110 )
1$
0#
#1225
0$
#1250
b1000 (
b1 !
b1 '
b100 "
b100 &
b111 )
1$
#1275
0$
#1300
b1001 (
b1 !
b1 '
b100 "
b100 &
b1000 )
1$
#1325
0$
#1350
b0 (
b1 !
b1 '
b10 "
b10 &
b1001 )
1$
1#
#1375
0$
#1400
b1 (
b100 !
b100 '
b1 "
b1 &
b0 )
1$
0#
